qutip_qip/__init__.py
qutip_qip/compat.py
qutip_qip/noise.py
qutip_qip/pulse.py
qutip_qip/qasm.py
qutip_qip/qubits.py
qutip_qip/version.py
qutip_qip/vqa.py
qutip_qip/algorithms/__init__.py
qutip_qip/algorithms/qft.py
qutip_qip/circuit/__init__.py
qutip_qip/circuit/_decompose.py
qutip_qip/circuit/base_renderer.py
qutip_qip/circuit/circuit.py
qutip_qip/circuit/circuitsimulator.py
qutip_qip/circuit/color_theme.py
qutip_qip/circuit/mat_renderer.py
qutip_qip/circuit/texrenderer.py
qutip_qip/circuit/text_renderer.py
qutip_qip/compiler/__init__.py
qutip_qip/compiler/cavityqedcompiler.py
qutip_qip/compiler/circuitqedcompiler.py
qutip_qip/compiler/gatecompiler.py
qutip_qip/compiler/instruction.py
qutip_qip/compiler/scheduler.py
qutip_qip/compiler/spinchaincompiler.py
qutip_qip/decompose/__init__.py
qutip_qip/decompose/_utility.py
qutip_qip/decompose/decompose_single_qubit_gate.py
qutip_qip/device/__init__.py
qutip_qip/device/cavityqed.py
qutip_qip/device/circuitqed.py
qutip_qip/device/modelprocessor.py
qutip_qip/device/optpulseprocessor.py
qutip_qip/device/processor.py
qutip_qip/device/spinchain.py
qutip_qip/operations/__init__.py
qutip_qip/operations/gateclass.py
qutip_qip/operations/gates.py
qutip_qip/operations/measurement.py
qutip_qip/qiskit/__init__.py
qutip_qip/qiskit/backend.py
qutip_qip/qiskit/converter.py
qutip_qip/qiskit/job.py
qutip_qip/qiskit/provider.py
qutip_qip/transpiler/__init__.py
qutip_qip/transpiler/chain.py
qutip_qip-0.4.0.dist-info/LICENSE
qutip_qip-0.4.0.dist-info/METADATA
qutip_qip-0.4.0.dist-info/WHEEL
qutip_qip-0.4.0.dist-info/top_level.txt
qutip_qip-0.4.0.dist-info/RECORD
