Metadata-Version: 2.1
Name: qutip-qip
Version: 0.4.0
Summary: The QuTiP quantum information processing package
Home-page: https://github.com/qutip/qutip-qip
Author: Alexander Pitchford, Paul D. Nation, Robert J. Johansson, Chris Granade, Arne Grimsmo, Nathan Shammah, Shahnawaz Ahmed, Neill Lambert, Eric Giguere, Boxi Li, Jake Lishman
Author-email: qutip-admin@googlegroups.com
License: BSD 3-Clause License
Keywords: quantum,physics,dynamics
Platform: Linux
Platform: Mac OSX
Platform: Unix
Platform: Windows
Classifier: Development Status :: 5 - Production/Stable
Classifier: Intended Audience :: Science/Research
Classifier: License :: OSI Approved :: BSD License
Classifier: Programming Language :: Python
Classifier: Programming Language :: Python :: 3
Classifier: Topic :: Scientific/Engineering
Classifier: Operating System :: MacOS
Classifier: Operating System :: POSIX
Classifier: Operating System :: Unix
Classifier: Operating System :: Microsoft :: Windows
License-File: LICENSE
Requires-Dist: numpy>=1.16.6
Requires-Dist: scipy>=1.0
Requires-Dist: qutip>=4.6
Requires-Dist: packaging
Provides-Extra: graphics
Requires-Dist: matplotlib>=1.3.0; extra == "graphics"
Provides-Extra: control
Requires-Dist: qutip-qtrl; extra == "control"
Provides-Extra: tests
Requires-Dist: pytest>=5.2; extra == "tests"
Provides-Extra: full
Requires-Dist: matplotlib>=1.3.0; extra == "full"
Requires-Dist: pytest>=5.2; extra == "full"
Requires-Dist: qutip-qtrl; extra == "full"
Provides-Extra: qiskit
Requires-Dist: qiskit<1.0.0; extra == "qiskit"
Requires-Dist: qiskit_aer; extra == "qiskit"
